tussik/dyno/__init__.py
tussik/dyno/attributes.py
tussik/dyno/connects.py
tussik/dyno/filtering.py
tussik/dyno/query.py
tussik/dyno/reading.py
tussik/dyno/table.py
tussik/dyno/transaction.py
tussik/dyno/update.py
tussik.dyno-0.1.0rc3.dist-info/LICENSE
tussik.dyno-0.1.0rc3.dist-info/METADATA
tussik.dyno-0.1.0rc3.dist-info/WHEEL
tussik.dyno-0.1.0rc3.dist-info/top_level.txt
tussik.dyno-0.1.0rc3.dist-info/zip-safe
tussik.dyno-0.1.0rc3.dist-info/RECORD
